<?xml version="1.0" encoding="UTF-8"?><codeTemplate version="4.4.2">
  <id>e8649d95-f5fd-4b03-9b26-68ddf23b4ab2</id>
  <name>Process XCA ITI-38 AdhocQueryRequest</name>
  <revision>2</revision>
  <lastModified>
    <time>1704310828567</time>
    <timezone>GMT</timezone>
  </lastModified>
  <contextSet>
    <delegate>
      <contextType>CHANNEL_PREPROCESSOR</contextType>
      <contextType>CHANNEL_UNDEPLOY</contextType>
      <contextType>DESTINATION_DISPATCHER</contextType>
      <contextType>CHANNEL_BATCH</contextType>
      <contextType>CHANNEL_POSTPROCESSOR</contextType>
      <contextType>SOURCE_FILTER_TRANSFORMER</contextType>
      <contextType>CHANNEL_ATTACHMENT</contextType>
      <contextType>DESTINATION_RESPONSE_TRANSFORMER</contextType>
      <contextType>SOURCE_RECEIVER</contextType>
      <contextType>DESTINATION_FILTER_TRANSFORMER</contextType>
      <contextType>CHANNEL_DEPLOY</contextType>
    </delegate>
  </contextSet>
  <properties class="com.mirth.connect.model.codetemplates.BasicCodeTemplateProperties">
    <type>FUNCTION</type>
    <code msync-fileref="Process XCA ITI-38 AdhocQueryRequest.js"/>
  </properties>
</codeTemplate>
